{
  "title": "Iran rejects Trump's proposal to end the war and lays out its own terms",
  "source": "https://www.npr.org/2026/03/26/nx-s1-5760941/iran-rejects-trumps-proposal-to-end-the-war-and-lays-out-its-own-terms",
  "author": "Daniel Estrin",
  "date": "2026-03-26",
  "body": "Iran's military command is rejecting a 15-point peace proposal from the U.S., saying it will not come to terms with Washington and laid out its own conditions. The United States offered sanctions relief if Iran were to end its nuclear program and take other steps. Iran says it does not plan to negotiate at all. White House press secretary Karoline Leavitt warned of further attacks if Iran does not accept a deal.\n\nThis is a 15-point proposal the U.S. drew up and gave to Iran via Pakistan. According to the proposal, Iran would need to end its nuclear program, stop supporting proxy militias in the Middle East, reopen the Strait of Hormuz completely, and limit its missile program. In exchange, Iran would get relief from sanctions. Essentially, these are the terms the U.S. came to Iran with before the war started.\n\nIran says it is rejecting this proposal. It says it does not even plan on holding negotiations, and it laid out its own terms. Iran countered the 15-point proposal from the U.S. with its own five-point proposal. The points include: no more war or killing Iranian leaders; guarantees there would be no further war against Iran; demanding reparations for war damages; an end to war on all fronts, including against all resistance groups in the region, a reference to Iran's proxies in Lebanon and Iraq; and asking for international guarantees of Iran's sovereign right to control the Strait of Hormuz.",
  "tags": ["geopolitics", "diplomacy", "iran", "usa"]
}
